demo/__init__.py
demo/app_settings.py
demo/local_settings.py
demo/sass_variables.py
demo/settings.py
demo/urls.py
demo/views.py
demo/wsgi.py
psu_infotext/__init__.py
psu_infotext/admin.py
psu_infotext/apps.py
psu_infotext/models.py
psu_infotext/tests.py
psu_infotext/urls.py
psu_infotext/views.py
psu_infotext/migrations/0001_initial.py
psu_infotext/migrations/0002_auto_20201102_1320.py
psu_infotext/migrations/0003_infotext_group_title.py
psu_infotext/migrations/0004_alter_infotext_id.py
psu_infotext/migrations/__init__.py
psu_infotext/services/__init__.py
psu_infotext/services/infotext_service.py
psu_infotext/templates/index.html
psu_infotext/templates/infotext_admin_links.html
psu_infotext/templates/infotext_index.html
psu_infotext/templates/psu_infotext/index.html
psu_infotext/templates/psu_infotext/index.js
psu_infotext/templatetags/__init__.py
psu_infotext/templatetags/infotext_taglib.py
psu_infotext-2.0.0.dist-info/METADATA
psu_infotext-2.0.0.dist-info/WHEEL
psu_infotext-2.0.0.dist-info/top_level.txt
psu_infotext-2.0.0.dist-info/RECORD
